dspace/__init__.py
dspace/dspace_client.py
dspace/dspace_objects.py
dspace/exceptions.py
dspace_client-0.3.1.dist-info/LICENSE
dspace_client-0.3.1.dist-info/METADATA
dspace_client-0.3.1.dist-info/WHEEL
dspace_client-0.3.1.dist-info/RECORD
